compositions/__init__.py
compositions/transform.py
compositions_coda-1.0.3.dist-info/LICENSE
compositions_coda-1.0.3.dist-info/METADATA
compositions_coda-1.0.3.dist-info/WHEEL
compositions_coda-1.0.3.dist-info/top_level.txt
compositions_coda-1.0.3.dist-info/RECORD
