Metadata-Version: 2.1
Name: compositions-coda
Version: 1.0.3
Summary: An extensive package for Compositional Data Analysis (CoDA)
Home-page: https://github.com/prablordeppey/compositions
Author: Ablordeppey Prosper
Author-email: prablordeppey@gmail.com
License: MIT
Project-URL: Bug Tracker, https://github.com/prablordeppey/compositions/issues
Platform: UNKNOWN
Classifier: Programming Language :: Python :: 3
Classifier: License :: OSI Approved :: MIT License
Classifier: Operating System :: OS Independent
Requires-Python: >=3.6
License-File: LICENSE
Requires-Dist: numpy (>=1.19.2)
